alphafed/__init__.py
alphafed/bass.py
alphafed/metrics_trace.py
alphafed/perf_bench.py
alphafed/scheduler.py
alphafed/utils.py
alphafed/contractor/__init__.py
alphafed/contractor/common.py
alphafed/contractor/task_contractor.py
alphafed/contractor/task_message_contractor.py
alphafed/data_channel/__init__.py
alphafed/data_channel/data_channel.py
alphafed/data_channel/data_channel_pb2.py
alphafed/data_channel/data_channel_pb2_grpc.py
alphafed/examples/fed_avg/clean_history_msg.py
alphafed/examples/fed_avg/demo_FedIRM.py
alphafed/examples/fed_avg/demo_task_dp.py
alphafed/examples/fed_avg/demos.py
alphafed/examples/fed_avg/run_aggregator.py
alphafed/examples/fed_avg/run_data_owner_3.py
alphafed/examples/fed_avg/run_data_owner_4.py
alphafed/examples/fed_avg/run_data_owner_5.py
alphafed/fed_avg/__init__.py
alphafed/fed_avg/contractor.py
alphafed/fed_avg/dp_contractor.py
alphafed/fed_avg/dp_fed_avg.py
alphafed/fed_avg/fed_avg.py
alphafed/fed_avg/secure_contractor.py
alphafed/fed_avg/secure_fed_avg.py
alphafed/secure/__init__.py
alphafed/secure/aes.py
alphafed/secure/ecdhe.py
alphafed/secure/shamir.py
alphafed/secure/tools.py
alphafed-0.1.1.dist-info/LICENSE
alphafed-0.1.1.dist-info/METADATA
alphafed-0.1.1.dist-info/WHEEL
alphafed-0.1.1.dist-info/top_level.txt
alphafed-0.1.1.dist-info/RECORD
