Metadata-Version: 2.1
Name: alphafed
Version: 0.1.1
Summary: AlphaMed Federated Learning Module
Author-email: Huang Yi Chun <huangyichun@jinghang.ai>
License: Apache License
Project-URL: Homepage, https://github.com/ssplabs/alphafed
Project-URL: Bug Tracker, https://github.com/ssplabs/alphafed/issues
Classifier: Programming Language :: Python :: 3
Classifier: License :: OSI Approved :: Apache Software License
Classifier: Operating System :: OS Independent
Requires-Python: >=3.8
License-File: LICENSE
Requires-Dist: cloudpickle (==2.0.0)
Requires-Dist: grpcio (==1.47.0)
Requires-Dist: protobuf (==4.21.4)
Requires-Dist: pycryptodome (==3.15.0)
Requires-Dist: requests (==2.28.1)
Requires-Dist: torch (==1.11.0)
Requires-Dist: torchvision (==0.12.0)
Requires-Dist: opacus (==1.1.3)
Requires-Dist: cryptography (==3.4.8)
Requires-Dist: concurrent-log-handler (==0.9.20)
